doordash_client/__init__.py
doordash_client/client.py
doordash_client/exceptions.py
doordash_client/models.py
doordash_client/tests/__init__.py
doordash_rest_client-0.1.3.dist-info/METADATA
doordash_rest_client-0.1.3.dist-info/WHEEL
doordash_rest_client-0.1.3.dist-info/licenses/LICENSE
doordash_rest_client-0.1.3.dist-info/RECORD
