Metadata-Version: 2.4
Name: doordash-rest-client
Version: 0.1.3
Summary: A comprehensive Python client for the DoorDash API
Project-URL: Homepage, https://github.com/doordash-automation/python-client
Project-URL: Documentation, https://doordash-automation.github.io/python-client/
Project-URL: Repository, https://github.com/doordash-automation/python-client.git
Project-URL: Issues, https://github.com/doordash-automation/python-client/issues
Project-URL: Changelog, https://github.com/doordash-automation/python-client/blob/main/CHANGELOG.md
Author-email: DoorDash Automation Suite <support@example.com>
Maintainer-email: DoorDash Automation Suite <support@example.com>
License: MIT License
License-File: LICENSE
Keywords: api,client,delivery,doordash,food,ordering
Classifier: Development Status :: 4 - Beta
Classifier: Intended Audience :: Developers
Classifier: License :: OSI Approved :: MIT License
Classifier: Operating System :: OS Independent
Classifier: Programming Language :: Python :: 3
Classifier: Programming Language :: Python :: 3.8
Classifier: Programming Language :: Python :: 3.9
Classifier: Programming Language :: Python :: 3.10
Classifier: Programming Language :: Python :: 3.11
Classifier: Programming Language :: Python :: 3.12
Classifier: Topic :: Internet :: WWW/HTTP :: HTTP Servers
Classifier: Topic :: Office/Business
Classifier: Topic :: Software Development :: Libraries :: Python Modules
Requires-Python: >=3.8
Requires-Dist: httpx>=0.24.0
Requires-Dist: pydantic>=2.0.0
Requires-Dist: typing-extensions>=4.0.0
Provides-Extra: async
Requires-Dist: aiofiles>=23.0.0; extra == 'async'
Provides-Extra: dev
Requires-Dist: black>=23.0.0; extra == 'dev'
Requires-Dist: isort>=5.12.0; extra == 'dev'
Requires-Dist: mypy>=1.0.0; extra == 'dev'
Requires-Dist: pytest-asyncio>=0.21.0; extra == 'dev'
Requires-Dist: pytest-cov>=4.0.0; extra == 'dev'
Requires-Dist: pytest>=7.0.0; extra == 'dev'
Requires-Dist: ruff>=0.0.280; extra == 'dev'
Provides-Extra: docs
Requires-Dist: mkdocs-material>=9.0.0; extra == 'docs'
Requires-Dist: mkdocs>=1.4.0; extra == 'docs'
Requires-Dist: mkdocstrings[python]>=0.20.0; extra == 'docs'
